setup.cfg
setup.py
bonoboapi/__init__.py
bonoboapi/facebookApiModule.py
bonoboapi/generalApiModule.py
bonoboapi/genericApiModule.py
bonoboapi/slackApiModule.py
bonoboapi/viberApiModule.py
bonoboapi.egg-info/PKG-INFO
bonoboapi.egg-info/SOURCES.txt
bonoboapi.egg-info/dependency_links.txt
bonoboapi.egg-info/not-zip-safe
bonoboapi.egg-info/requires.txt
bonoboapi.egg-info/top_level.txt