Metadata-Version: 1.1
Name: bonoboapi
Version: 0.1
Summary: bonobo API for sending messages to Bonobo.ai
Home-page: UNKNOWN
Author: bonobo
Author-email: ohad@bonobo.ai
License: ?
Platform: UNKNOWN
Classifier: Programming Language :: Python :: 2
Classifier: Programming Language :: Python :: 3
